aockit/__init__.py
aockit/download.py
aockit/exceptions.py
aockit/misc.py
aockit/settings.py
aockit/template.py
aoc_kit-0.1.5.dist-info/entry_points.txt
aoc_kit-0.1.5.dist-info/LICENSE
aoc_kit-0.1.5.dist-info/WHEEL
aoc_kit-0.1.5.dist-info/METADATA
aoc_kit-0.1.5.dist-info/RECORD
