Metadata-Version: 2.1
Name: aoc-kit
Version: 0.1.5
Summary: Toolkit for advent of code
Author: Pierre Hoffmeister
Author-email: pierre.git@posteo.de
Requires-Python: >=3.10,<4.0
Classifier: Programming Language :: Python :: 3
Classifier: Programming Language :: Python :: 3.10
Classifier: Programming Language :: Python :: 3.11
Requires-Dist: python-dotenv (>=0.21.0,<0.22.0)
Requires-Dist: requests (>=2.28.1,<3.0.0)
